Metadata-Version: 2.4
Name: dstz
Version: 0.0.7
Summary: 一个轻量、易用的Python证据理论库，专注于Dempster-Shafer理论及其扩展。
Author-email: Tianxiang Zhan <zhantianxianguestc@hotmail.com>
License: MIT License
Project-URL: Homepage, https://github.com/ztxtech/dstz
Project-URL: Repository, https://github.com/ztxtech/dstz
Keywords: evidence theory,Dempster-Shafer,belief functions,information fusion,uncertainty,reasoning,Deng entropy
Classifier: Development Status :: 4 - Beta
Classifier: Programming Language :: Python :: 3
Classifier: Programming Language :: Python :: 3.7
Classifier: Programming Language :: Python :: 3.8
Classifier: Programming Language :: Python :: 3.9
Classifier: Programming Language :: Python :: 3.10
Classifier: Programming Language :: Python :: 3.11
Classifier: License :: OSI Approved :: MIT License
Classifier: Operating System :: OS Independent
Classifier: Intended Audience :: Developers
Classifier: Intended Audience :: Science/Research
Classifier: Topic :: Scientific/Engineering
Classifier: Topic :: Software Development :: Libraries :: Python Modules
Requires-Python: >=3.7
License-File: LICENSE
Requires-Dist: numpy
Dynamic: license-file
